almetro/__init__.py
almetro/al.py
almetro/algorithms.py
almetro/chart.py
almetro/complexity.py
almetro/instance.py
almetro/metro.py
almetro/spec.py
almetro/table.py
almetro-1.0.7.dist-info/LICENSE
almetro-1.0.7.dist-info/METADATA
almetro-1.0.7.dist-info/WHEEL
almetro-1.0.7.dist-info/top_level.txt
almetro-1.0.7.dist-info/RECORD
