Metadata-Version: 2.1
Name: almetro
Version: 1.0.7
Summary: A python library to measure algorithms execution time and compare with its theoretical complexity
Home-page: https://github.com/arnour/almetro
Author: Arnour Sabino
Author-email: arnour.sabino@gmail.com
License: Apache License
Platform: UNKNOWN
Requires-Dist: matplotlib (==3.0.3)
Requires-Dist: tabulate (==0.8.3)
Provides-Extra: test
Requires-Dist: flake8 (>=3.7.7) ; extra == 'test'
Requires-Dist: flake8-print (>=3.1.0) ; extra == 'test'
Requires-Dist: coverage (>=4.5.3) ; extra == 'test'
Requires-Dist: PyHamcrest (>=1.9.0) ; extra == 'test'
